src/pytile/__init__.py
src/pytile/mask_col.py
src/pytile/pytile.py
src/pytile/pytile_tools.py
src/pytile/pytile_utils.py
pytile_game_engine-1.1.5.dist-info/LICENSE
pytile_game_engine-1.1.5.dist-info/METADATA
pytile_game_engine-1.1.5.dist-info/WHEEL
pytile_game_engine-1.1.5.dist-info/top_level.txt
pytile_game_engine-1.1.5.dist-info/RECORD
